setup.py
py_ls/__init__.py
py_ls.egg-info/PKG-INFO
py_ls.egg-info/SOURCES.txt
py_ls.egg-info/dependency_links.txt
py_ls.egg-info/top_level.txt
py_ls/constructs/__init__.py
py_ls/constructs/constructs.py
py_ls/pattern_matching/__init__.py
py_ls/pattern_matching/pattern_matching.py
py_ls/sl_containers/__init__.py
py_ls/sl_containers/sl_option.py
py_ls/sl_containers/sl_try.py
py_ls/sl_containers/sl_validation.py
tests/pattern_matching/__init__.py
tests/pattern_matching/test_pattern_matching.py
tests/sl_containers/__init__.py
tests/sl_containers/test_option_container.py
tests/sl_containers/test_try_container.py
tests/sl_containers/test_validation_container.py