Metadata-Version: 1.0
Name: py-ls
Version: 1.0.0
Summary: Python likes scala
Home-page: https://github.com/Szala---/pyls
Author: Pawel Szalapski
Author-email: szalapski.pawel@gmail.com
License: UNKNOWN
Platform: UNKNOWN
